ferro/__init__.py
ferro/data.py
ferro/models.py
Ferro-0.3.0.dist-info/METADATA
Ferro-0.3.0.dist-info/WHEEL
Ferro-0.3.0.dist-info/license.txt
Ferro-0.3.0.dist-info/top_level.txt
Ferro-0.3.0.dist-info/RECORD
