Metadata-Version: 2.1
Name: Ferro
Version: 0.3.0
Summary: Manipulation and Modeling of Ferroelectric Test Data
Home-page: https://github.com/JAnderson419/Ferro
Author: Jackson Anderson
Author-email: jda4923@rit.edu
License: Creative Commons Attribution-NonCommercial-ShareAlike 4.0 International
Download-URL: https://github.com/JAnderson419/Ferro/archive/0.3.0.tar.gz
Platform: UNKNOWN
Requires-Dist: scipy
Requires-Dist: numpy
Requires-Dist: matplotlib
Requires-Dist: mpldatacursor
